.gitignore
setup.py
tox.ini
girder_tape_archive/__init__.py
girder_tape_archive.egg-info/PKG-INFO
girder_tape_archive.egg-info/SOURCES.txt
girder_tape_archive.egg-info/dependency_links.txt
girder_tape_archive.egg-info/entry_points.txt
girder_tape_archive.egg-info/requires.txt
girder_tape_archive.egg-info/top_level.txt
girder_tape_archive/web_client/TarExportView.js
girder_tape_archive/web_client/TarImportView.js
girder_tape_archive/web_client/exportButton.pug
girder_tape_archive/web_client/import.pug
girder_tape_archive/web_client/import.styl
girder_tape_archive/web_client/importMenu.pug
girder_tape_archive/web_client/main.js
girder_tape_archive/web_client/package.json
girder_tape_archive/web_client/tarExport.pug
girder_tape_archive/web_client/tarImport.pug